[
  {
    "Id": 1,
    "FirstName": "Ram1",
    "LastName": "Gopal1",
    "Email": "Gopal1@gmail.com"
  },
  {
    "Id": 2,
    "FirstName": "Ram2",
    "LastName": "Gopal2",
    "Email": "Gopal2@gmail.com"
  },
  {
    "Id": 3,
    "FirstName": "Ram3",
    "LastName": "Gopal3",
    "Email": "Gopal3@gmail.com"
  },
  {
    "Id": 4,
    "FirstName": "Ram4",
    "LastName": "Gopal4",
    "Email": "Gopal4@gmail.com"
  },
  {
    "Id": 5,
    "FirstName": "Ram5",
    "LastName": "Gopal5",
    "Email": "Gopal5@gmail.com"
  }
]